{
  "clientmsg": {
    "success": {
      "activity": {
        "save": "Attività salvata"
      },
      "activityPlan": {
        "save": "Attività programmate",
        "join": "Attività pianificate",
        "invite": "Sei stato/a invitato/a {{email}} a questa attività",
        "delete": "Attività cancellata",
        "sampleInvitationSent": "Invito inviato a {{email}}"
      },
      "templateCampaign": {
        "save": null
      }
    },
    "error": {
      "activity": {
        "join": "Questa attività non puo' essere pianificata"
      }
    }
  },
  "list": {
    "planAnActivity": "Programma un'attivitä",
    "createNewActivity": "Crea una nuova attività",
    "search": "Cerca",
    "setFocus": "Focus su",
    "areas": "Aree",
    "togetherWith": "Insieme a",
    "alone": "Me stesso",
    "asAGroup": "come un gruppo",
    "duration": "Durata",
    "lt15min": "< 15 min",
    "15-30min": "15-30 min",
    "30-60min": "30 min - 1 ora",
    "mt60min": "piu' di un'ora",
    "rating": "Voto",
    "activities": "Attività",
    "recommendedForYou": "Raccomandato per te",
    "campaignActivities": "Attività della campagna",
    "all": "Tutti",
    "ofTotal": "del totale",
    "done": "Fatto",
    "recommended": "Raccomandato",
    "planned": "Pianificato",
    "ifYouFillAssessment": "Compilando la valutazione, saremo in grado di fornirti raccomandazioni adatte a te",
    "toAssessment": "Vai all'auto-controllo",
    "showAllActivities": "Mostra tutte le attività",
    "planIt": "Pianificalo",
    "notForMe": "Non per me!"
  },
  "admin": {
    "navigation": {
      "start": "Inizio",
      "activities": "Attività"
    },
    "matrix": {
      "header": "Valutazione, raccomandazioni per le domande: ",
      "recommendationSliderLeft": "Raccomandazione <br/>Parte sinistra",
      "recommendationSliderRight": "Raccomandazione <br/>Parte destra",
      "valueRangeHint": "Valori da 0 a 10<br/>0 = not raccomandato, 10 = raccomandato"
    },
    "templateCampaign": {
      "addOffer": null,
      "header": null,
      "remove": null,
      "save": null,
      "type": {
        "Invitation": null,
        "Recommendation": null
      },
      "week": null,
      "weekday": null
    }
  },
  "visibility": {
    "public": "Pubblico",
    "campaign": "Campagna",
    "private": "Privato"
  },
  "source": {
    "youpers": "YOUPERS",
    "community": "Comunità",
    "campaign": "Campagna"
  },
  "calendarNotification": {
    "none": "Nessuna notifica",
    "0": "Orario di inizio",
    "300": "5 minuti prima",
    "600": "10 minuti prima",
    "900": "15 minuti prima",
    "1800": "30 minuti prima",
    "3600": "1 ora prima",
    "7200": "2 ore prima",
    "86400": "1 giorno prima",
    "172800": "2 giorni prima"
  },
  "activityPlanInvite": {
    "header": "Benvenuto - Piattaforma digitale per la salute ed il benessere di YouPers",
    "subheader": " ti ha invitato ad unirti ad un'attività.",
    "inviteMessage": "Per unirti a questa attività <a {{loginLinkAttribute}}>autenticati</a> o <a href='' {{registerLinkAttribute}}>registrati</a>"
  },
  "activityPlanFrequency": {
    "once": "Una volta",
    "day": "Giornalmente",
    "week": "Settimanalmente",
    "month": "Mensilmente",
    "year": "Annualmente"
  },
  "activityPlanEditable": {
    "editable": "Cambia un'attività pianificata",
    "notEditableJoinedPlan": "Consiglio: questa attività non puo' essere modificata perchè altri utenti si sono già uniti",
    "notEditablePastEvent": "Consiglio: questa attività non puo' essere modificata perchè è già stata eseguita"
  },
  "activityPlanDeletable": {
    "deletable": "Cancella un'attività programmata",
    "deletableOnlyFutureEvents": "Cancella future pianificazioni",
    "notDeletableNoFutureEvents": "Suggerimento: Questa attività non può essere cancellata perché tutti gli eventi sono nel passato."
  },
  "activityField": {
    "awarenessAbility": "Consapevolezza e abilità",
    "timeManagement": "Gestione del tempo",
    "workStructuring": "Sistemazione lavorativa",
    "physicalActivity": "Attività fisica",
    "nutrition": "Nutrizione",
    "leisureActivity": "Attività nel tempo libero",
    "breaks": "Pause",
    "relaxation": "Relax",
    "socialInteraction": "Interazione sociale"
  },
  "executiontype": {
    "self": "Da solo",
    "group": "Gruppo"
  }
}